pridepy/__init__.py
pridepy/aspera/etc/aspera-license
pridepy/aspera/etc/aspera.conf
pridepy/aspera/key/aspera_tokenauth_id_rsa
pridepy/aspera/key/asperaweb_id_dsa.openssh
pridepy/aspera/linux-32/ascmd
pridepy/aspera/linux-32/ascp
pridepy/aspera/linux-32/ascp4
pridepy/aspera/linux-32/aspshell
pridepy/aspera/linux-32/astokengen
pridepy/aspera/linux-32/faspstream
pridepy/aspera/linux-64/ascmd
pridepy/aspera/linux-64/ascp
pridepy/aspera/linux-64/ascp4
pridepy/aspera/linux-64/aspshell
pridepy/aspera/linux-64/astokengen
pridepy/aspera/linux-64/faspstream
pridepy/aspera/mac-intel/ascmd
pridepy/aspera/mac-intel/ascp
pridepy/aspera/mac-intel/aspshell
pridepy/aspera/mac-intel/astokengen
pridepy/aspera/windows-32/ascmd.exe
pridepy/aspera/windows-32/ascp.exe
pridepy/aspera/windows-32/ascp4.exe
pridepy/aspera/windows-32/aspshell.exe
pridepy/aspera/windows-32/astokengen.exe
pridepy/aspera/windows-32/fasp3.dll
pridepy/aspera/windows-32/faspstream.exe
pridepy/aspera/windows-32/libeay32.dll
pridepy/aspera/windows-32/msvcp100.dll
pridepy/aspera/windows-32/msvcr100.dll
pridepy/aspera/windows-32/ssleay32.dll
pridepy/aspera/windows-64/ascp.exe
pridepy/aspera/windows-64/ascp4.exe
pridepy/aspera/windows-64/fasp3.dll
pridepy/aspera/windows-64/faspstream.exe
pridepy/aspera/windows-64/libeay32.dll
pridepy/aspera/windows-64/msvcp100.dll
pridepy/aspera/windows-64/msvcr100.dll
pridepy/aspera/windows-64/ssleay32.dll
pridepy/authentication/__init__.py
pridepy/authentication/authentication.py
pridepy/files/__init__.py
pridepy/files/files.py
pridepy/pridepy.py
pridepy/project/__init__.py
pridepy/project/project.py
pridepy/spectra/__init__.py
pridepy/spectra/spectra.py
pridepy/statistics/__init__.py
pridepy/statistics/statistics.py
pridepy/tests/__init__.py
pridepy/tests/test_authentication.py
pridepy/tests/test_raw_files.py
pridepy/tests/test_search.py
pridepy/util/__init__.py
pridepy/util/api_handling.py
pridepy/util/file_handling.py
pridepy-0.0.11.dist-info/METADATA
pridepy-0.0.11.dist-info/WHEEL
pridepy-0.0.11.dist-info/entry_points.txt
pridepy-0.0.11.dist-info/licenses/LICENSE
pridepy-0.0.11.dist-info/RECORD
