Metadata-Version: 2.4
Name: pridepy
Version: 0.0.11
Summary: Python Client library for PRIDE Rest API
License: Apache-2.0
License-File: LICENSE
Keywords: PRIDE,proteomics,mass-spectrometry,API,big data,bioinformatics,data science
Author: PRIDE Team
Author-email: pride-support@ebi.ac.uk
Maintainer: PRIDE Team
Maintainer-email: pride-support@ebi.ac.uk
Requires-Python: >=3.9,<4.0
Classifier: Development Status :: 5 - Production/Stable
Classifier: Intended Audience :: Science/Research
Classifier: License :: OSI Approved :: Apache Software License
Classifier: Operating System :: OS Independent
Classifier: Programming Language :: Python :: 3
Classifier: Programming Language :: Python :: 3.9
Classifier: Programming Language :: Python :: 3.10
Classifier: Programming Language :: Python :: 3.11
Classifier: Programming Language :: Python :: 3.12
Classifier: Programming Language :: Python :: 3.13
Classifier: Programming Language :: Python :: 3.14
Classifier: Programming Language :: Python :: 3 :: Only
Classifier: Programming Language :: Python :: 3.7
Classifier: Programming Language :: Python :: 3.8
Classifier: Topic :: Scientific/Engineering :: Bio-Informatics
Requires-Dist: boto3 (>=1.34.0,<2.0.0)
Requires-Dist: botocore (>=1.34.0,<2.0.0)
Requires-Dist: click (>=8.1.7,<9.0.0)
Requires-Dist: httpx (>=0.27.0,<0.28.0)
Requires-Dist: plotly (>=5.18.0,<6.0.0)
Requires-Dist: ratelimit (>=2.2.1,<3.0.0)
Requires-Dist: requests (>=2.31.0,<3.0.0)
Requires-Dist: tqdm (>=4.66.1,<5.0.0)
Project-URL: Documentation, https://github.com/PRIDE-Archive/pridepy#readme
Project-URL: License, https://github.com/PRIDE-Archive/pridepy/LICENSE
Project-URL: PyPI, https://pypi.org/project/pridepy/
Project-URL: PRIDE, https://www.ebi.ac.uk/pride/archive/
Project-URL: Repository, https://github.com/PRIDE-Archive/pridepy
